README
setup.py
pyxmpp2_scram/__init__.py
pyxmpp2_scram/core.py
pyxmpp2_scram/exceptions.py
pyxmpp2_scram/scram.py
pyxmpp2_scram.egg-info/PKG-INFO
pyxmpp2_scram.egg-info/SOURCES.txt
pyxmpp2_scram.egg-info/dependency_links.txt
pyxmpp2_scram.egg-info/top_level.txt